PythonProjectBootstrapperTest3/EntryPoint.py
PythonProjectBootstrapperTest3/Math.py
PythonProjectBootstrapperTest3/__init__.py
PythonProjectBootstrapperTest3-0.1.5.dist-info/LICENSE.txt
PythonProjectBootstrapperTest3-0.1.5.dist-info/METADATA
PythonProjectBootstrapperTest3-0.1.5.dist-info/WHEEL
PythonProjectBootstrapperTest3-0.1.5.dist-info/entry_points.txt
PythonProjectBootstrapperTest3-0.1.5.dist-info/top_level.txt
PythonProjectBootstrapperTest3-0.1.5.dist-info/RECORD
